stealth_chopper/__init__.py
stealth_chopper/animation.py
stealth_chopper/common_url.py
stealth_chopper/extraction.py
stealth_chopper/listenOnSomeOne.py
stealth_chopper/process_pcap.py
stealth_chopper/recon_scan.py
stealth_chopper/validation.py
stealth_chopper/assets/__init__.py
stealth_chopper/assets/tld.txt
stealth_chopper/assets/url_file.txt
stealth_chopper-4.1.2.dist-info/licenses/LICENSE
stealth_chopper-4.1.2.dist-info/METADATA
stealth_chopper-4.1.2.dist-info/WHEEL
stealth_chopper-4.1.2.dist-info/entry_points.txt
stealth_chopper-4.1.2.dist-info/top_level.txt
stealth_chopper-4.1.2.dist-info/RECORD
