Metadata-Version: 2.4
Name: stealth-chopper
Version: 4.1.2
Summary: Aggressive Sniffer & MITM Launcher
License-Expression: MIT
Requires-Python: >=3.8
License-File: LICENSE
Requires-Dist: tabulate
Requires-Dist: Beautifulsoup4
Requires-Dist: requests
Requires-Dist: colorama
Requires-Dist: pyfiglet
Requires-Dist: termcolor
Requires-Dist: psutil
Requires-Dist: scapy
Requires-Dist: dnspython
Requires-Dist: mac-vendor-lookup
Requires-Dist: python-dotenv
Dynamic: license-file
